distilling_flask/__init__.py
distilling_flask/app.py
distilling_flask/cli.py
distilling_flask/config.py
distilling_flask/messages.py
distilling_flask/models.py
distilling_flask/tasks.py
distilling_flask/wsgi.py
distilling_flask/conf/__init__.py
distilling_flask/main/__init__.py
distilling_flask/main/errors.py
distilling_flask/main/views.py
distilling_flask/migrations/README
distilling_flask/migrations/alembic.ini
distilling_flask/migrations/env.py
distilling_flask/migrations/script.py.mako
distilling_flask/migrations/versions/01decae7c1ec_.py
distilling_flask/migrations/versions/236a616b9d9e_.py
distilling_flask/migrations/versions/2b03e9148ec7_add_ngp_ms.py
distilling_flask/migrations/versions/54244e85a2ad_add_storage_models.py
distilling_flask/migrations/versions/7356c906381a_manual_migration_for_acct_activity_.py
distilling_flask/migrations/versions/acd9f5a6d982_create_user_settings_table_with_default_.py
distilling_flask/migrations/versions/fbad678c93bd_acct_to_activity_relationship.py
distilling_flask/migrations/versions/fe6fd20811ba_.py
distilling_flask/plotlydash/__init__.py
distilling_flask/plotlydash/aio_components.py
distilling_flask/plotlydash/app.py
distilling_flask/plotlydash/figure_layout.py
distilling_flask/plotlydash/layout.py
distilling_flask/plotlydash/plots.py
distilling_flask/plotlydash/util.py
distilling_flask/plotlydash/pages/__init__.py
distilling_flask/plotlydash/pages/analyze_file.py
distilling_flask/plotlydash/pages/saved_activity.py
distilling_flask/plotlydash/pages/saved_table.py
distilling_flask/plotlydash/pages/settings.py
distilling_flask/plotlydash/pages/storage_table.py
distilling_flask/plotlydash/pages/strava_activity.py
distilling_flask/plotlydash/pages/strava_settings.py
distilling_flask/plotlydash/pages/strava_table.py
distilling_flask/plotlydash/pages/training_log.py
distilling_flask/plotlydash/pages/training_stress.py
distilling_flask/strava_api/__init__.py
distilling_flask/strava_api/views.py
distilling_flask/util/__init__.py
distilling_flask-0.0.1a1.dist-info/LICENSE
distilling_flask-0.0.1a1.dist-info/METADATA
distilling_flask-0.0.1a1.dist-info/WHEEL
distilling_flask-0.0.1a1.dist-info/top_level.txt
distilling_flask-0.0.1a1.dist-info/RECORD
