Metadata-Version: 2.1
Name: distilling-flask
Version: 0.0.1a1
Summary: Personal running data analysis and visualization, powered by Flask, Dash, and Pandas.
Author-email: Aaron Schroeder <aaron@trailzealot.com>
License: Copyright 2022 Aaron Schroeder
Project-URL: Homepage, https://github.com/aaron-schroeder/distilling-flask
Classifier: License :: OSI Approved :: MIT License
Classifier: Programming Language :: Python
Classifier: Programming Language :: Python :: 3
Requires-Python: >=3.8
License-File: LICENSE
Requires-Dist: dash (>=2.5.0)
Requires-Dist: dash-bootstrap-components (>=1.0.0)
Requires-Dist: Flask (>=2.1.0)
